{"@timestamp":"2020-11-10T16:02:19.880+00:00","severity":"INFO","service":"hello-service","trace":"","span":"","exportable":"","pid":"26206","thread":"AsyncResolver-bootstrap-executor-0","class":"c.n.d.s.r.aws.ConfigClusterResolver","rest":"Resolving eureka endpoints via configuration"}
{"@timestamp":"2020-11-10T16:05:11.021+00:00","severity":"INFO","service":"hello-service","trace":"bf00f66f86b2957f","span":"1f0af8dd3fb95d6a","exportable":"true","pid":"26206","thread":"http-nio-8085-exec-7","class":"class com.ken.controller.HelloController","rest":"============<hello>,TraceId=,SpanId============"}
{"@timestamp":"2020-11-10T16:05:11.028+00:00","severity":"INFO","service":"hello-service","trace":"bf00f66f86b2957f","span":"1f0af8dd3fb95d6a","exportable":"true","pid":"26206","thread":"http-nio-8085-exec-7","class":"class com.ken.controller.HelloController","rest":"bf00f66f86b2957f"}
{"@timestamp":"2020-11-10T16:05:11.029+00:00","severity":"INFO","service":"hello-service","trace":"bf00f66f86b2957f","span":"1f0af8dd3fb95d6a","exportable":"true","pid":"26206","thread":"http-nio-8085-exec-7","class":"class com.ken.controller.HelloController","rest":"1f0af8dd3fb95d6a"}
{"@timestamp":"2020-11-10T16:07:20.109+00:00","severity":"INFO","service":"hello-service","trace":"","span":"","exportable":"","pid":"26206","thread":"AsyncResolver-bootstrap-executor-0","class":"c.n.d.s.r.aws.ConfigClusterResolver","rest":"Resolving eureka endpoints via configuration"}
{"@timestamp":"2020-11-10T16:12:20.118+00:00","severity":"INFO","service":"hello-service","trace":"","span":"","exportable":"","pid":"26206","thread":"AsyncResolver-bootstrap-executor-0","class":"c.n.d.s.r.aws.ConfigClusterResolver","rest":"Resolving eureka endpoints via configuration"}
{"@timestamp":"2020-11-10T16:17:20.130+00:00","severity":"INFO","service":"hello-service","trace":"","span":"","exportable":"","pid":"26206","thread":"AsyncResolver-bootstrap-executor-0","class":"c.n.d.s.r.aws.ConfigClusterResolver","rest":"Resolving eureka endpoints via configuration"}
{"@timestamp":"2020-11-10T16:22:20.139+00:00","severity":"INFO","service":"hello-service","trace":"","span":"","exportable":"","pid":"26206","thread":"AsyncResolver-bootstrap-executor-0","class":"c.n.d.s.r.aws.ConfigClusterResolver","rest":"Resolving eureka endpoints via configuration"}
{"@timestamp":"2020-11-10T16:27:20.148+00:00","severity":"INFO","service":"hello-service","trace":"","span":"","exportable":"","pid":"26206","thread":"AsyncResolver-bootstrap-executor-0","class":"c.n.d.s.r.aws.ConfigClusterResolver","rest":"Resolving eureka endpoints via configuration"}
{"@timestamp":"2020-11-10T16:32:20.157+00:00","severity":"INFO","service":"hello-service","trace":"","span":"","exportable":"","pid":"26206","thread":"AsyncResolver-bootstrap-executor-0","class":"c.n.d.s.r.aws.ConfigClusterResolver","rest":"Resolving eureka endpoints via configuration"}
{"@timestamp":"2020-11-10T16:37:20.166+00:00","severity":"INFO","service":"hello-service","trace":"","span":"","exportable":"","pid":"26206","thread":"AsyncResolver-bootstrap-executor-0","class":"c.n.d.s.r.aws.ConfigClusterResolver","rest":"Resolving eureka endpoints via configuration"}
{"@timestamp":"2020-11-10T16:42:20.175+00:00","severity":"INFO","service":"hello-service","trace":"","span":"","exportable":"","pid":"26206","thread":"AsyncResolver-bootstrap-executor-0","class":"c.n.d.s.r.aws.ConfigClusterResolver","rest":"Resolving eureka endpoints via configuration"}
{"@timestamp":"2020-11-10T16:47:20.185+00:00","severity":"INFO","service":"hello-service","trace":"","span":"","exportable":"","pid":"26206","thread":"AsyncResolver-bootstrap-executor-0","class":"c.n.d.s.r.aws.ConfigClusterResolver","rest":"Resolving eureka endpoints via configuration"}
{"@timestamp":"2020-11-10T16:52:20.196+00:00","severity":"INFO","service":"hello-service","trace":"","span":"","exportable":"","pid":"26206","thread":"AsyncResolver-bootstrap-executor-0","class":"c.n.d.s.r.aws.ConfigClusterResolver","rest":"Resolving eureka endpoints via configuration"}
{"@timestamp":"2020-11-10T16:57:20.208+00:00","severity":"INFO","service":"hello-service","trace":"","span":"","exportable":"","pid":"26206","thread":"AsyncResolver-bootstrap-executor-0","class":"c.n.d.s.r.aws.ConfigClusterResolver","rest":"Resolving eureka endpoints via configuration"}
{"@timestamp":"2020-11-10T17:02:20.216+00:00","severity":"INFO","service":"hello-service","trace":"","span":"","exportable":"","pid":"26206","thread":"AsyncResolver-bootstrap-executor-0","class":"c.n.d.s.r.aws.ConfigClusterResolver","rest":"Resolving eureka endpoints via configuration"}
